pypkgs_test/__init__.py
pypkgs_test/pypkgs_test.py
pypkgs_test-0.1.0.dist-info/LICENSE
pypkgs_test-0.1.0.dist-info/WHEEL
pypkgs_test-0.1.0.dist-info/METADATA
pypkgs_test-0.1.0.dist-info/RECORD
